habitex/__init__.py
habitex/archive_explorer.py
habitex/hz_plots.py
habitex-1.0.0.dist-info/licenses/LICENSE
habitex-1.0.0.dist-info/METADATA
habitex-1.0.0.dist-info/WHEEL
habitex-1.0.0.dist-info/top_level.txt
habitex-1.0.0.dist-info/RECORD
